BigKindsParser/__init__.py
BigKindsParser/_version.py
BigKindsParser/preprocessing.py
BigKindsParser/visualization.py
BigKindsParser-0.1.5.dist-info/LICENSE
BigKindsParser-0.1.5.dist-info/METADATA
BigKindsParser-0.1.5.dist-info/WHEEL
BigKindsParser-0.1.5.dist-info/top_level.txt
BigKindsParser-0.1.5.dist-info/RECORD
