Metadata-Version: 2.1
Name: BigKindsParser
Version: 0.1.5
Summary: Journalism, preprocessing-data.
Home-page: https://github.com/sorrychoe/BigKindsParser
Author: Sorrychoe
License: MIT
Project-URL: Source Code, https://github.com/sorrychoe/BigKindsParser
Project-URL: Bug Tracker, https://github.com/sorrychoe/BigKindsParser/issues
Keywords: Journalism,preprocessing-data,BigKinds
Requires-Python: >=3.7
License-File: LICENSE
Requires-Dist: matplotlib (>=3.5.3)
Requires-Dist: pandas (==1.5.2)
Requires-Dist: wordcloud (>=1.8.2.2)
Provides-Extra: dev
Requires-Dist: flake8 (>=3.9) ; extra == 'dev'
Requires-Dist: isort (>=5.7) ; extra == 'dev'
Requires-Dist: pre-commit (>=2.13) ; extra == 'dev'
Requires-Dist: pylint (>=2.9) ; extra == 'dev'
